cordy/__init__.py
cordy/auth.py
cordy/client.py
cordy/errors.py
cordy/events.py
cordy/gateway.py
cordy/http.py
cordy/models/__init__.py
cordy/models/intents.py
cordy/py.typed
cordy/runner.py
cordy/types.py
cordy/util.py
cordy.py-0.1.0.dev3.dist-info/LICENSE
cordy.py-0.1.0.dev3.dist-info/WHEEL
cordy.py-0.1.0.dev3.dist-info/METADATA
cordy.py-0.1.0.dev3.dist-info/RECORD
